{
  "buildCommand" : {
    "command" : "build",
    "skipDependencies" : false,
    "style" : "buildOnly"
  },
  "configuredTargets" : [
    {
      "guid" : "de73c5af120885cce55ae56de29a1f16e2be703405edd7ba8cdc6c423f55570f"
    }
  ],
  "containerPath" : "/Users/stefanieagahari/Documents/Alex 2.0/TestingGameVisual.xcodeproj",
  "continueBuildingAfterErrors" : false,
  "dependencyScope" : "workspace",
  "enableIndexBuildArena" : false,
  "hideShellScriptEnvironment" : false,
  "parameters" : {
    "action" : "build",
    "activeArchitecture" : "undefined_arch",
    "activeRunDestination" : {
      "disableOnlyActiveArch" : true,
      "platform" : "iphoneos",
      "sdk" : "iphoneos26.2",
      "sdkVariant" : "iphoneos",
      "supportedArchitectures" : [
        "armv4t",
        "armv5",
        "armv6",
        "armv7",
        "armv7f",
        "armv7s",
        "armv7k",
        "arm64",
        "arm64e"
      ],
      "targetArchitecture" : "undefined_arch"
    },
    "arenaInfo" : {
      "buildIntermediatesPath" : "/Users/stefanieagahari/Documents/Alex 2.0/.derivedData/Build/Intermediates.noindex",
      "buildProductsPath" : "/Users/stefanieagahari/Documents/Alex 2.0/.derivedData/Build/Products",
      "derivedDataPath" : "/Users/stefanieagahari/Documents/Alex 2.0/.derivedData",
      "indexDataStoreFolderPath" : "/Users/stefanieagahari/Documents/Alex 2.0/.derivedData/Index.noindex/DataStore",
      "indexEnableDataStore" : true,
      "indexPCHPath" : "/Users/stefanieagahari/Documents/Alex 2.0/.derivedData/Index.noindex/PrecompiledHeaders",
      "pchPath" : "/Users/stefanieagahari/Documents/Alex 2.0/.derivedData/Build/Intermediates.noindex/PrecompiledHeaders"
    },
    "configurationName" : "Debug",
    "overrides" : {
      "commandLine" : {
        "table" : {
          "CODE_SIGNING_ALLOWED" : "NO"
        }
      },
      "synthesized" : {
        "table" : {
          "ACTION" : "build",
          "ENABLE_PREVIEWS" : "NO",
          "ENABLE_XOJIT_PREVIEWS" : "YES",
          "ONLY_ACTIVE_ARCH" : "YES"
        }
      }
    }
  },
  "schemeCommand" : "launch",
  "showNonLoggedProgress" : true,
  "useDryRun" : false,
  "useImplicitDependencies" : true,
  "useLegacyBuildLocations" : false,
  "useParallelTargets" : true
}